.gitignore
.python-version
LICENSE
Makefile
README.md
conftest.py
renovate.json
setup.cfg
setup.py
auth_gitlab/__init__.py
auth_gitlab/apps.py
auth_gitlab/client.py
auth_gitlab/constants.py
auth_gitlab/provider.py
auth_gitlab/views.py
sentry_auth_gitlab_v2.egg-info/PKG-INFO
sentry_auth_gitlab_v2.egg-info/SOURCES.txt
sentry_auth_gitlab_v2.egg-info/dependency_links.txt
sentry_auth_gitlab_v2.egg-info/entry_points.txt
sentry_auth_gitlab_v2.egg-info/not-zip-safe
sentry_auth_gitlab_v2.egg-info/requires.txt
sentry_auth_gitlab_v2.egg-info/top_level.txt