Metadata-Version: 2.4
Name: sentry-auth-gitlab-v2
Version: 0.5.0
Summary: Gitlab authentication provider for Sentry
Home-page: https://github.com/zekker6/sentry-auth-gitlab
Author: Zakhar Bessarab
Author-email: me@zekker.dev
Classifier: Intended Audience :: Developers
Classifier: Intended Audience :: System Administrators
Classifier: Operating System :: OS Independent
Classifier: Topic :: Software Development
License-File: LICENSE
Requires-Dist: sentry
Provides-Extra: tests
Requires-Dist: pytest; extra == "tests"
Requires-Dist: mock; extra == "tests"
Dynamic: author
Dynamic: author-email
Dynamic: classifier
Dynamic: description
Dynamic: description-content-type
Dynamic: home-page
Dynamic: license-file
Dynamic: provides-extra
Dynamic: requires-dist
Dynamic: summary
